dottorrent/__init__.py
dottorrent/exceptions.py
dottorrent/version.py
dottorrent-1.10.1.dist-info/DESCRIPTION.rst
dottorrent-1.10.1.dist-info/METADATA
dottorrent-1.10.1.dist-info/RECORD
dottorrent-1.10.1.dist-info/WHEEL
dottorrent-1.10.1.dist-info/metadata.json
dottorrent-1.10.1.dist-info/top_level.txt
